kwimage/__init__.py
kwimage/__main__.py
kwimage/_backend_info.py
kwimage/_common.py
kwimage/_im_color_data.py
kwimage/_im_color_data.pyi
kwimage/_internal.py
kwimage/_internal.pyi
kwimage/_typing.py
kwimage/_typing.pyi
kwimage/im_alphablend.py
kwimage/im_alphablend.pyi
kwimage/im_color.py
kwimage/im_color.pyi
kwimage/im_core.py
kwimage/im_core.pyi
kwimage/im_cv2.py
kwimage/im_cv2.pyi
kwimage/im_demodata.py
kwimage/im_demodata.pyi
kwimage/im_draw.py
kwimage/im_draw.pyi
kwimage/im_filter.py
kwimage/im_filter.pyi
kwimage/im_io.py
kwimage/im_io.pyi
kwimage/im_itk.py
kwimage/im_runlen.py
kwimage/im_runlen.pyi
kwimage/im_stack.py
kwimage/im_stack.pyi
kwimage/im_transform.py
kwimage/py.typed
kwimage/transform.py
kwimage/transform.pyi
kwimage/util_warp.py
kwimage/util_warp.pyi
kwimage/algo/__init__.py
kwimage/algo/algo_nms.py
kwimage/algo/algo_nms.pyi
kwimage/algo/_nms_backend/__init__.py
kwimage/algo/_nms_backend/py_nms.py
kwimage/algo/_nms_backend/py_nms.pyi
kwimage/algo/_nms_backend/torch_nms.py
kwimage/algo/_nms_backend/torch_nms.pyi
kwimage/cli/__init__.py
kwimage/cli/__main__.py
kwimage/cli/crop_border.py
kwimage/cli/stack_images.py
kwimage/cli/stack_images.pyi
kwimage/structs/__init__.py
kwimage/structs/_generic.py
kwimage/structs/_generic.pyi
kwimage/structs/boxes.py
kwimage/structs/boxes.pyi
kwimage/structs/coords.py
kwimage/structs/coords.pyi
kwimage/structs/detections.py
kwimage/structs/detections.pyi
kwimage/structs/heatmap.py
kwimage/structs/heatmap.pyi
kwimage/structs/mask.py
kwimage/structs/mask.pyi
kwimage/structs/points.py
kwimage/structs/points.pyi
kwimage/structs/polygon.py
kwimage/structs/polygon.pyi
kwimage/structs/segmentation.py
kwimage/structs/segmentation.pyi
kwimage/structs/single_box.py
kwimage/structs/single_box.pyi
kwimage-0.11.6.dist-info/licenses/LICENSE
kwimage-0.11.6.dist-info/METADATA
kwimage-0.11.6.dist-info/WHEEL
kwimage-0.11.6.dist-info/entry_points.txt
kwimage-0.11.6.dist-info/top_level.txt
kwimage-0.11.6.dist-info/RECORD
